pydantic_glue/__init__.py
pydantic_glue/cli.py
pydantic_glue/errors.py
pydantic_glue/handler.py
pydantic_glue-0.7.0.dist-info/METADATA
pydantic_glue-0.7.0.dist-info/WHEEL
pydantic_glue-0.7.0.dist-info/entry_points.txt
pydantic_glue-0.7.0.dist-info/licenses/LICENSE
pydantic_glue-0.7.0.dist-info/RECORD
