Metadata-Version: 2.4
Name: pydantic-glue
Version: 0.7.0
Summary: Convert pydantic model to aws glue schema for terraform
License: MIT
License-File: LICENSE
Keywords: pydantic,glue,athena,types,convert
Author: Serhii Dimchenko
Author-email: svdimchenko@gmail.com
Requires-Python: >=3.9,<4.0
Classifier: License :: OSI Approved :: MIT License
Classifier: Programming Language :: Python :: 3
Classifier: Programming Language :: Python :: 3.9
Classifier: Programming Language :: Python :: 3.10
Classifier: Programming Language :: Python :: 3.11
Classifier: Programming Language :: Python :: 3.12
Classifier: Programming Language :: Python :: 3.13
Classifier: Programming Language :: Python :: 3.14
Requires-Dist: jsonref (>=1.1.0,<2.0.0)
Requires-Dist: pydantic (>=2.7.1,<3.0.0)
Project-URL: Bug Tracker, https://github.com/svdimchenko/pydantic-glue/issues
Project-URL: Repository, https://github.com/svdimchenko/pydantic-glue
Project-URL: Releases, https://github.com/svdimchenko/pydantic-glue/releases
